scala/__init__.py
scala/content_manager/__init__.py
scala/player/__init__.py
scala/utils/__init__.py
scala/utils/typedef.py
scala_wrapper/__init__.py
scala_wrapper/content_manager/__init__.py
scala_wrapper/player/__init__.py
scala_wrapper/utils/__init__.py
scala_wrapper/utils/typedef.py
scala_wrapper-0.0.6.dist-info/METADATA
scala_wrapper-0.0.6.dist-info/WHEEL
scala_wrapper-0.0.6.dist-info/top_level.txt
scala_wrapper-0.0.6.dist-info/RECORD
